{
    "AUTOERT": [
        {
            "hash": 139671,
            "original": "HOME",
            "translated": "主页",
            "desc": ""
        },
        {
            "hash": 103919314,
            "original": "Adjustable seats, Air conditioning, Alloy wheels, CD Player, Central locking, Electric mirrors, Electric windows, Full service history, Leather upholstery, Immobilizer.",
            "translated": "可调节座椅，空调，铬合金轮毂，CD播放机，中控锁，电动后视镜，电动车窗，提供完整维修保养记录，真皮内饰，防盗器。",
            "desc": ""
        },
        {
            "hash": 148679939,
            "original": "2003 INTRUDER 4.3l V8 Limited",
            "translated": "2003 INTRUDER 4.3l V8 Limited",
            "desc": ""
        },
        {
            "hash": 519226968,
            "original": "CONTACT US",
            "translated": "联系我们",
            "desc": ""
        },
        {
            "hash": 583786725,
            "original": "2001 SCHAFTER 6.5l V12 SC",
            "translated": "2001 SCHAFTER 6.5l V12 SC",
            "desc": ""
        },
        {
            "hash": 609938212,
            "original": "4 Doors, Manual, 26,000 miles, Metallic Turquoise. 12 months parts and labor warranty. Insurance. 0% DEPOSIT finance available. Ask Derek for full quotation. Licensed credit broker. Written details available.",
            "translated": "4门，手动挡，里程26,000英里，金属绿喷漆。12个月保修。有保险。支持0首付购车。请向Derek询问报价。持牌信贷经纪人。提供书面详细信息。",
            "desc": ""
        },
        {
            "hash": 636530783,
            "original": "CALL - 662-555-0147",
            "translated": "电话 - 662-555-0147",
            "desc": ""
        },
        {
            "hash": 649828647,
            "original": "CALL - 265-555-2423",
            "translated": "电话 - 265-555-2423",
            "desc": ""
        },
        {
            "hash": 716246107,
            "original": "ABOUT",
            "translated": "关于",
            "desc": ""
        },
        {
            "hash": 802897410,
            "original": "Air conditioning, Alarm, Body colored bumpers, Drivers airbag, Electric door mirrors. 1 previous owner. CD/cassete, mint condition. All enquiries / viewing must be between 8am to 9pm.",
            "translated": "空调，报警器，塑料保险杠，主副驾驶座安全气囊，电动后视镜。二手买入。CD/磁带机，品相完美。只在上午8点至晚上9点接受咨询或看车。",
            "desc": ""
        },
        {
            "hash": 930953898,
            "original": "$130995",
            "translated": "$130995",
            "desc": ""
        },
        {
            "hash": 1409696597,
            "original": "2004 PRESIDENTE 4.5l V10",
            "translated": "2004 PRESIDENTE 4.5l V10",
            "desc": ""
        },
        {
            "hash": 1628868056,
            "original": "$62995",
            "translated": "$62995",
            "desc": ""
        },
        {
            "hash": 1690297544,
            "original": "2001 TURISMO 4.0l Quad Cam V8",
            "translated": "2001 TURISMO 4.0l Quad Cam V8",
            "desc": ""
        },
        {
            "hash": 2109490979,
            "original": "$42999",
            "translated": "$42999",
            "desc": ""
        },
        {
            "hash": 2321080412,
            "original": "CALL - 265-555-2423",
            "translated": "电话 - 265-555-2423",
            "desc": ""
        },
        {
            "hash": 2371872366,
            "original": "CALL - 265-555-2423",
            "translated": "电话 - 265-555-2423",
            "desc": ""
        },
        {
            "hash": 2895791957,
            "original": "2003 FELTZER 3.8 Supercharged V8",
            "translated": "2003 FELTZER 3.8 Supercharged V8",
            "desc": ""
        },
        {
            "hash": 3415587227,
            "original": "Stunning Black metallic, alloys, front driving lamps, full electrics, CD Player, central locking, exceptional condition throughout.",
            "translated": "金属黑喷漆，铬合金轮毂，前大灯，电动车，CD播放器，中控锁，车况良好。",
            "desc": ""
        },
        {
            "hash": 3496690502,
            "original": "2 Doors, Manual 5 speed, Petrol, 26,000 miles, Rosso Red, Adjustable seats, Alloy wheels, CD Player, Central locking, Electric windows, Cream Leather. Rear Spoiler and ABS.",
            "translated": "2门，5挡手动，汽油车，里程26,000英里，罗索红色，可调节座椅，铬合金轮毂，CD播放器，中控锁，电动车窗，奶油色真皮内饰。后扰流板和ABS。",
            "desc": ""
        },
        {
            "hash": 3780437273,
            "original": "Automatic, 37,000 miles, Metallic Silver. Air-Conditioning, ABS, Alloy wheels, Cruise control, Full service history, Leather seats.",
            "translated": "自动挡，里程37,000英里，金属银喷漆。空调，ABS，铬合金轮毂，定速巡航，提供完整维修保养记录，真皮座椅。",
            "desc": ""
        },
        {
            "hash": 3998595648,
            "original": "VIEW CARS",
            "translated": "查看车辆",
            "desc": ""
        },
        {
            "hash": 4103144560,
            "original": "2006 PMP600 600ci V8 Semi",
            "translated": "2006 PMP600 600ci V8 Semi",
            "desc": ""
        },
        {
            "hash": 4147775934,
            "original": "2001 BANSHEE 300ci V8 Twin Turbo GT",
            "translated": "2001 BANSHEE 300ci V8 Twin Turbo GT",
            "desc": ""
        },
        {
            "hash": 4233960249,
            "original": "Automatic, Diesel, 8000 miles, Metallic Silver. Leather seats, ABS, Air conditioning, Alloy wheels, CD Multichanger, Cruise control, Heated seats, Multi function steering wheel, Navigation system, Park distance control.",
            "translated": "自动挡，柴油车，里程8000英里，金属银车身。真皮座椅，ABS，空调，铬合金轮毂，CD播放器，定速巡航，加热座椅，多功能方向盘，导航系统，停车距离控制。",
            "desc": ""
        }
    ]
}
